{"cameraMode":{"drawMode":0,"name":"Shaded","section":"Shading Mode"},"sceneLighting":true,"audioPlay":false,"sceneViewState":{"showFog":true,"showMaterialUpdate":false,"showSkybox":true,"showFlares":true,"showImageEffects":true,"showParticleSystems":true},"in2DMode":false,"pivot":{"x":50.288002014160159,"y":1.2892717123031617,"z":51.276206970214847},"rotation":{"x":-0.07968313992023468,"y":0.8884537220001221,"z":-0.16885130107402802,"w":-0.41928502917289736},"size":2.0804455280303957,"orthographic":false}